Compiled from "test01.java"
public class test01 {
  public test01();
    Code:
       0: aload_0
       1: invokespecial #1                  // Method java/lang/Object."<init>":()V
       4: return

  public static void main(java.lang.String[]);
    Code:
       0: new           #2                  // class test01
       3: dup
       4: invokespecial #3                  // Method "<init>":()V
       7: astore_1
       8: aload_1
       9: invokevirtual #4                  // Method t1:()V
      12: aload_1
      13: invokevirtual #5                  // Method t2:()V
      16: aload_1
      17: invokevirtual #6                  // Method t4:()V
      20: aload_1
      21: invokevirtual #7                  // Method t5:()V
      24: return

  public void t1();
    Code:
       0: ldc           #8                  // float 0.100000024f
       2: fstore_1
       3: ldc           #9                  // float 0.099999964f
       5: fstore_2
       6: getstatic     #10                 // Field java/lang/System.out:Ljava/io/PrintStream;
       9: ldc           #11                 // String t1()==================
      11: invokevirtual #12                 // Method java/io/PrintStream.println:(Ljava/lang/String;)V
      14: getstatic     #10                 // Field java/lang/System.out:Ljava/io/PrintStream;
      17: fload_1
      18: invokevirtual #13                 // Method java/io/PrintStream.println:(F)V
      21: getstatic     #10                 // Field java/lang/System.out:Ljava/io/PrintStream;
      24: fload_2
      25: invokevirtual #13                 // Method java/io/PrintStream.println:(F)V
      28: fload_1
      29: fload_2
      30: fcmpl
      31: ifne          45
      34: getstatic     #10                 // Field java/lang/System.out:Ljava/io/PrintStream;
      37: ldc           #14                 // String true
      39: invokevirtual #12                 // Method java/io/PrintStream.println:(Ljava/lang/String;)V
      42: goto          53
      45: getstatic     #10                 // Field java/lang/System.out:Ljava/io/PrintStream;
      48: ldc           #15                 // String false
      50: invokevirtual #12                 // Method java/io/PrintStream.println:(Ljava/lang/String;)V
      53: getstatic     #10                 // Field java/lang/System.out:Ljava/io/PrintStream;
      56: ldc           #11                 // String t1()==================
      58: invokevirtual #12                 // Method java/io/PrintStream.println:(Ljava/lang/String;)V
      61: return

  public void t2();
    Code:
       0: ldc           #8                  // float 0.100000024f
       2: invokestatic  #16                 // Method java/lang/Float.valueOf:(F)Ljava/lang/Float;
       5: astore_1
       6: ldc           #9                  // float 0.099999964f
       8: invokestatic  #16                 // Method java/lang/Float.valueOf:(F)Ljava/lang/Float;
      11: astore_2
      12: getstatic     #10                 // Field java/lang/System.out:Ljava/io/PrintStream;
      15: ldc           #17                 // String t2()===========
      17: invokevirtual #12                 // Method java/io/PrintStream.println:(Ljava/lang/String;)V
      20: getstatic     #10                 // Field java/lang/System.out:Ljava/io/PrintStream;
      23: aload_1
      24: invokevirtual #18                 // Method java/io/PrintStream.println:(Ljava/lang/Object;)V
      27: getstatic     #10                 // Field java/lang/System.out:Ljava/io/PrintStream;
      30: aload_2
      31: invokevirtual #18                 // Method java/io/PrintStream.println:(Ljava/lang/Object;)V
      34: aload_1
      35: aload_2
      36: invokevirtual #19                 // Method java/lang/Float.equals:(Ljava/lang/Object;)Z
      39: ifeq          53
      42: getstatic     #10                 // Field java/lang/System.out:Ljava/io/PrintStream;
      45: ldc           #14                 // String true
      47: invokevirtual #12                 // Method java/io/PrintStream.println:(Ljava/lang/String;)V
      50: goto          61
      53: getstatic     #10                 // Field java/lang/System.out:Ljava/io/PrintStream;
      56: ldc           #15                 // String false
      58: invokevirtual #12                 // Method java/io/PrintStream.println:(Ljava/lang/String;)V
      61: getstatic     #10                 // Field java/lang/System.out:Ljava/io/PrintStream;
      64: ldc           #17                 // String t2()===========
      66: invokevirtual #12                 // Method java/io/PrintStream.println:(Ljava/lang/String;)V
      69: return

  public void t3();
    Code:
       0: aconst_null
       1: astore_1
       2: aload_1
       3: astore_2
       4: iconst_m1
       5: istore_3
       6: aload_2
       7: invokevirtual #20                 // Method java/lang/String.hashCode:()I
      10: lookupswitch  { // 1
               3392903: 28
               default: 39
          }
      28: aload_2
      29: ldc           #21                 // String null
      31: invokevirtual #22                 // Method java/lang/String.equals:(Ljava/lang/Object;)Z
      34: ifeq          39
      37: iconst_0
      38: istore_3
      39: iload_3
      40: lookupswitch  { // 1
                     0: 60
               default: 71
          }
      60: getstatic     #10                 // Field java/lang/System.out:Ljava/io/PrintStream;
      63: ldc           #21                 // String null
      65: invokevirtual #12                 // Method java/io/PrintStream.println:(Ljava/lang/String;)V
      68: goto          79
      71: getstatic     #10                 // Field java/lang/System.out:Ljava/io/PrintStream;
      74: ldc           #23                 // String default
      76: invokevirtual #12                 // Method java/io/PrintStream.println:(Ljava/lang/String;)V
      79: return

  public void t4();
    Code:
       0: new           #24                 // class java/math/BigDecimal
       3: dup
       4: ldc2_w        #25                 // double 0.1d
       7: invokespecial #27                 // Method java/math/BigDecimal."<init>":(D)V
      10: astore_1
      11: getstatic     #10                 // Field java/lang/System.out:Ljava/io/PrintStream;
      14: aload_1
      15: invokevirtual #18                 // Method java/io/PrintStream.println:(Ljava/lang/Object;)V
      18: new           #24                 // class java/math/BigDecimal
      21: dup
      22: ldc           #28                 // String 0.1
      24: invokespecial #29                 // Method java/math/BigDecimal."<init>":(Ljava/lang/String;)V
      27: astore_2
      28: getstatic     #10                 // Field java/lang/System.out:Ljava/io/PrintStream;
      31: aload_2
      32: invokevirtual #18                 // Method java/io/PrintStream.println:(Ljava/lang/Object;)V
      35: return

  public void t5();
    Code:
       0: getstatic     #30                 // Field lock:Ljava/util/concurrent/locks/Lock;
       3: invokeinterface #31,  1           // InterfaceMethod java/util/concurrent/locks/Lock.tryLock:()Z
       8: pop
       9: getstatic     #30                 // Field lock:Ljava/util/concurrent/locks/Lock;
      12: invokeinterface #32,  1           // InterfaceMethod java/util/concurrent/locks/Lock.unlock:()V
      17: goto          47
      20: astore_1
      21: aload_1
      22: invokevirtual #34                 // Method java/lang/Exception.printStackTrace:()V
      25: getstatic     #30                 // Field lock:Ljava/util/concurrent/locks/Lock;
      28: invokeinterface #32,  1           // InterfaceMethod java/util/concurrent/locks/Lock.unlock:()V
      33: goto          47
      36: astore_2
      37: getstatic     #30                 // Field lock:Ljava/util/concurrent/locks/Lock;
      40: invokeinterface #32,  1           // InterfaceMethod java/util/concurrent/locks/Lock.unlock:()V
      45: aload_2
      46: athrow
      47: return
    Exception table:
       from    to  target type
           0     9    20   Class java/lang/Exception
           0     9    36   any
          20    25    36   any

  static {};
    Code:
       0: new           #35                 // class java/util/concurrent/locks/ReentrantLock
       3: dup
       4: invokespecial #36                 // Method java/util/concurrent/locks/ReentrantLock."<init>":()V
       7: putstatic     #30                 // Field lock:Ljava/util/concurrent/locks/Lock;
      10: return
}
